<Properties StartupConfiguration="{8EB4B90D-1CD4-4880-A297-0263273F8A78}|Default">
  <MonoDevelop.Ide.Workbench ActiveDocument="../../../../usr/share/dotnet/sdk/NuGetFallbackFolder/microsoft.aspnetcore.razor.design/2.2.0/build/netstandard2.0/Microsoft.AspNetCore.Razor.Design.CodeGeneration.targets">
    <Files>
      <File FileName="../../../../usr/share/dotnet/sdk/NuGetFallbackFolder/microsoft.aspnetcore.razor.design/2.2.0/build/netstandard2.0/Microsoft.AspNetCore.Razor.Design.CodeGeneration.targets" Line="123" Column="5" />
    </Files>
    <Pads>
      <Pad Id="ProjectPad">
        <State name="__root__">
          <Node name="aspcoresergio" expanded="True">
            <Node name="aspcoresergio" expanded="True">
              <Node name="Controllers" expanded="True" />
              <Node name="Properties" expanded="True" />
              <Node name="Views" expanded="True">
                <Node name="Home" expanded="True" />
              </Node>
              <Node name="wwwroot" expanded="True" />
              <Node name="Startup.cs" selected="True" />
            </Node>
          </Node>
        </State>
      </Pad>
      <Pad Id="MonoDevelop.Debugger.WatchPad">
        <State />
      </Pad>
    </Pads>
  </MonoDevelop.Ide.Workbench>
  <MonoDevelop.Ide.DebuggingService.PinnedWatches />
  <MonoDevelop.Ide.Workspace ActiveConfiguration="Debug" />
  <MonoDevelop.Ide.ItemProperties.aspcoresergio PreferredExecutionTarget="MonoDevelop.Default" />
  <MonoDevelop.Ide.DebuggingService.Breakpoints>
    <BreakpointStore />
  </MonoDevelop.Ide.DebuggingService.Breakpoints>
  <MultiItemStartupConfigurations />
</Properties>